MANIFEST.in
README.md
pyproject.toml
requirements.txt
setup.cfg
setup.py
versioneer.py
gitgerrit/__init__.py
gitgerrit/_version.py
gitgerrit/gitgerrit.py
gitgerrit/logger.py
gitgerrit.egg-info/PKG-INFO
gitgerrit.egg-info/SOURCES.txt
gitgerrit.egg-info/dependency_links.txt
gitgerrit.egg-info/entry_points.txt
gitgerrit.egg-info/requires.txt
gitgerrit.egg-info/top_level.txt