Metadata-Version: 2.1
Name: gitgerrit
Version: 0.0.9
Summary: Command line tool to interact with gerrit change requests
Home-page: https://github.com/rasjani/gitgerrit
Author: Jani Mikkonen
Author-email: jani.mikkonen@gmail.com
License: Apache License 2.0
Keywords: git gerrit ci
Platform: any
Classifier: Development Status :: 3 - Alpha
Classifier: Operating System :: OS Independent
Classifier: License :: OSI Approved :: Apache Software License
Classifier: Programming Language :: Python
Classifier: Programming Language :: Python :: 3
Classifier: Programming Language :: Python :: 3.6
Classifier: Programming Language :: Python :: 3.7
